bertini/__init__.py
bertini/_pybertini.cpython-313-darwin.so
bertini/_version.py
bertini/algorithms/__init__.py
bertini/algorithms/zerodim.py
bertini/container/__init__.py
bertini/endgame/__init__.py
bertini/endgame/config/__init__.py
bertini/function_tree/__init__.py
bertini/function_tree/root/__init__.py
bertini/function_tree/symbol/__init__.py
bertini/include/bertini2/bertini.hpp
bertini/include/bertini2/blackbox/algorithm_builder.hpp
bertini/include/bertini2/blackbox/argc_argv.hpp
bertini/include/bertini2/blackbox/config.hpp
bertini/include/bertini2/blackbox/global_configs.hpp
bertini/include/bertini2/blackbox/main_mode_switch.hpp
bertini/include/bertini2/blackbox/switches_zerodim.hpp
bertini/include/bertini2/blackbox/user_homotopy.hpp
bertini/include/bertini2/classic.hpp
bertini/include/bertini2/common/config.hpp
bertini/include/bertini2/common/stream_enum.hpp
bertini/include/bertini2/detail/configured.hpp
bertini/include/bertini2/detail/enable_permuted_arguments.hpp
bertini/include/bertini2/detail/events.hpp
bertini/include/bertini2/detail/is_template_parameter.hpp
bertini/include/bertini2/detail/observable.hpp
bertini/include/bertini2/detail/observer.hpp
bertini/include/bertini2/detail/typelist.hpp
bertini/include/bertini2/detail/visitable.hpp
bertini/include/bertini2/detail/visitor.hpp
bertini/include/bertini2/double_extensions.hpp
bertini/include/bertini2/eigen_extensions.hpp
bertini/include/bertini2/eigen_serialization_addon.hpp
bertini/include/bertini2/endgames/amp_endgame.hpp
bertini/include/bertini2/endgames/base_endgame.hpp
bertini/include/bertini2/endgames/cauchy.hpp
bertini/include/bertini2/endgames/config.hpp
bertini/include/bertini2/endgames/events.hpp
bertini/include/bertini2/endgames/fixed_prec_endgame.hpp
bertini/include/bertini2/endgames/interpolation.hpp
bertini/include/bertini2/endgames/observers.hpp
bertini/include/bertini2/endgames/powerseries.hpp
bertini/include/bertini2/endgames/prec_base.hpp
bertini/include/bertini2/endgames.hpp
pybertini-1.0.3.dist-info/METADATA
pybertini-1.0.3.dist-info/WHEEL
pybertini-1.0.3.dist-info/RECORD
