Metadata-Version: 2.2
Name: pybertini
Version: 1.0.3
Summary: Software for numerical algebraic geometry
Author: Bertini Team
Maintainer-Email: silviana amethyst <amethyst@mpi-cbg.de>
Project-URL: Repository, https://github.com/bertiniteam/b2
Requires-Python: >=3.11
Requires-Dist: numpy
Requires-Dist: eigenpy
Provides-Extra: test
Requires-Dist: pytest; extra == "test"
